awscli_mate/__init__.py
awscli_mate/_version.py
awscli_mate/api.py
awscli_mate/awscli.py
awscli_mate/cli.py
awscli_mate/constants.py
awscli_mate/exc.py
awscli_mate/paths.py
awscli_mate/search.py
awscli_mate/ui.py
awscli_mate/url.py
awscli_mate/docs/__init__.py
awscli_mate/tests/__init__.py
awscli_mate/tests/helper.py
awscli_mate/tests/paths.py
awscli_mate/vendor/__init__.py
awscli_mate/vendor/better_fuzzywuzzy.py
awscli_mate/vendor/os_platform.py
awscli_mate-1.1.3.dist-info/AUTHORS.rst
awscli_mate-1.1.3.dist-info/LICENSE.txt
awscli_mate-1.1.3.dist-info/METADATA
awscli_mate-1.1.3.dist-info/WHEEL
awscli_mate-1.1.3.dist-info/entry_points.txt
awscli_mate-1.1.3.dist-info/top_level.txt
awscli_mate-1.1.3.dist-info/RECORD
